powervaultpy/__init__.py
powervaultpy/powervault.py
powervaultpy-0.0.8.dist-info/METADATA
powervaultpy-0.0.8.dist-info/WHEEL
powervaultpy-0.0.8.dist-info/top_level.txt
powervaultpy-0.0.8.dist-info/RECORD
