Metadata-Version: 2.1
Name: powervaultpy
Version: 0.0.8
Summary: An integration to control the Powervault battery
Author-email: Adam McDonagh <adam@elitemonkey.net>
License: GPLv3
Project-URL: Homepage, https://github.com/adammcdonagh/powervaultpy
Project-URL: Bug Tracker, https://github.com/adammcdonagh/powervaultpy/issues
Project-URL: Changelog, https://github.com/adammcdonagh/powervaultpy/blob/main/CHANGELOG.md
Keywords: powervault,home,automation
Classifier: Programming Language :: Python :: 3
Classifier: License :: OSI Approved :: GNU General Public License v3 (GPLv3)
Classifier: Operating System :: POSIX
Requires-Python: >=3.9
Requires-Dist: requests (>=2.28)
Requires-Dist: pytz
Provides-Extra: dev
Requires-Dist: black (>=23.1.0) ; extra == 'dev'
Requires-Dist: isort ; extra == 'dev'
Requires-Dist: pytest ; extra == 'dev'
Requires-Dist: pytest-env ; extra == 'dev'
Requires-Dist: pytest-asyncio ; extra == 'dev'
Requires-Dist: bumpver ; extra == 'dev'
Requires-Dist: pre-commit ; extra == 'dev'
